AUTHORS.rst
CONTRIBUTING.rst
HISTORY.rst
LICENSE
MANIFEST.in
README.rst
setup.cfg
setup.py
lovd/__init__.py
lovd/leiden_database.py
lovd/utilities.py
lovd.egg-info/PKG-INFO
lovd.egg-info/SOURCES.txt
lovd.egg-info/dependency_links.txt
lovd.egg-info/not-zip-safe
lovd.egg-info/top_level.txt