Metadata-Version: 1.1
Name: lovd
Version: 0.1.0
Summary: Tools for extracting variants from Leiden Open Variation Database Installations.
Home-page: https://github.com/andrewhill157/lovd
Author: Andrew Hill
Author-email: andrewhill157@gmail.com
License: BSD
Keywords: lovd
Platform: UNKNOWN
Classifier: Development Status :: 2 - Pre-Alpha
Classifier: Intended Audience :: Developers
Classifier: License :: OSI Approved :: BSD License
Classifier: Natural Language :: English
Classifier: Programming Language :: Python :: 2
Classifier: Programming Language :: Python :: 2.6
Classifier: Programming Language :: Python :: 2.7
Classifier: Programming Language :: Python :: 3
Classifier: Programming Language :: Python :: 3.3
